{"timestamp": 120.00000000149012, "ITS_PDU_Header": {"tmp": "tmp"}, "Basic_Container": {"tmp": "tmp"}, "HF_Container": {"sumo_id": "99", "location": [-271.9754638671875, -2.0], "speed": [-2719.754598144373, -19.99999970197678, 0], "yaw": -179.99996948242188}, "LF_Container": {"tmp": "tmp"}, "Special_Vehicle_Container": {"tmp": "tmp"}, "option": {"size": 190, "type": "CAM"}}
{"timestamp": 120.10000000298024, "ITS_PDU_Header": {"tmp": "tmp"}, "Basic_Container": {"tmp": "tmp"}, "HF_Container": {"sumo_id": "99", "location": [-273.92718505859375, -2.0], "speed": [-19.517211623233383, 0.0, 0], "yaw": -179.99996948242188}, "LF_Container": {"tmp": "tmp"}, "Special_Vehicle_Container": {"tmp": "tmp"}, "option": {"size": 190, "type": "CAM"}}
{"timestamp": 120.20000000447035, "ITS_PDU_Header": {"tmp": "tmp"}, "Management_Container": {"tmp": "tmp"}, "Station_Data_Container": {"sumo_id": "99", "location": [-275.88079833984375, -2.0], "speed": [-19.53613252138894, 0.0, 0], "yaw": -179.99996948242188}, "Sensor_Information_Container": [0, 1, 2, 3], "Perceived_Object_Container": [{"time": 120.20000000447035, "location": {"x": -276.39542967818863, "y": -9.242784221478644}, "speed": {"x": -17.301025132819635, "y": 0.0, "z": 0}, "pseudonym": 0}, {"time": 120.20000000447035, "location": {"x": -402.61213513852726, "y": -2.1953636912095336}, "speed": {"x": -18.219299044917538, "y": 0.0, "z": 0}, "pseudonym": 1}, {"time": 120.20000000447035, "location": {"x": -305.6518942870402, "y": 5.542211828259142}, "speed": {"x": 4.077148376745755, "y": 0.0, "z": 0}, "pseudonym": 2}, {"time": 120.20000000447035, "location": {"x": -388.0398869261414, "y": -5.6527586478783665}, "speed": {"x": -17.237853747042212, "y": 0.0, "z": 0}, "pseudonym": 3}, {"time": 120.20000000447035, "location": {"x": -348.47803897934136, "y": 6.095135284533283}, "speed": {"x": 14.619140407157833, "y": 0.0, "z": 0}, "pseudonym": 4}, {"time": 120.20000000447035, "location": {"x": -306.31145666367513, "y": 5.351566182926308}, "speed": {"x": 4.077148376745755, "y": 0.0, "z": 0}, "pseudonym": 2}, {"time": 120.20000000447035, "location": {"x": -253.3077863115756, "y": 9.147113946031736}, "speed": {"x": 19.31030244662907, "y": 0.0, "z": 0}, "pseudonym": 5}, {"time": 120.20000000447035, "location": {"x": -155.80654118179936, "y": 5.5082265736856915}, "speed": {"x": 18.45886202962902, "y": 0.0, "z": 0}, "pseudonym": 6}], "option": {"size": 541, "type": "CPM"}}
{"timestamp": 120.30000000596047, "ITS_PDU_Header": {"tmp": "tmp"}, "Management_Container": {"tmp": "tmp"}, "Station_Data_Container": {"sumo_id": "99", "location": [-277.83294677734375, -2.0], "speed": [-19.521484084107218, 0.0, 0], "yaw": -179.99996948242188}, "Sensor_Information_Container": [0, 1, 2, 3], "Perceived_Object_Container": [{"time": 120.30000000596047, "location": {"x": -163.70802327622613, "y": -1.3180603479346744}, "speed": {"x": -15.953979254454683, "y": 0.0, "z": 0}, "pseudonym": 7}, {"time": 120.30000000596047, "location": {"x": -306.9266434646968, "y": 5.026814239778286}, "speed": {"x": 4.290161068884118, "y": 0.0, "z": 0}, "pseudonym": 8}], "option": {"size": 331, "type": "CPM"}}
{"timestamp": 120.40000000745059, "ITS_PDU_Header": {"tmp": "tmp"}, "Basic_Container": {"tmp": "tmp"}, "HF_Container": {"sumo_id": "99", "location": [-279.7926025390625, -2.0], "speed": [-19.59655732517604, 0.0, 0], "yaw": -179.99996948242188}, "LF_Container": {"tmp": "tmp"}, "Special_Vehicle_Container": {"tmp": "tmp"}, "option": {"size": 190, "type": "CAM"}}
{"timestamp": 120.5000000089407, "ITS_PDU_Header": {"tmp": "tmp"}, "Management_Container": {"tmp": "tmp"}, "Station_Data_Container": {"sumo_id": "99", "location": [-281.7541198730469, -2.0], "speed": [-19.615173047554894, 0.0, 0], "yaw": -179.99996948242188}, "Sensor_Information_Container": [0, 1, 2, 3], "Perceived_Object_Container": [{"time": 120.5000000089407, "location": {"x": -303.7946179869775, "y": 5.646625264863009}, "speed": {"x": 4.647216727626074, "y": 0.0, "z": 0}, "pseudonym": 2}], "option": {"size": 296, "type": "CPM"}}
{"timestamp": 120.60000001043082, "ITS_PDU_Header": {"tmp": "tmp"}, "Management_Container": {"tmp": "tmp"}, "Station_Data_Container": {"sumo_id": "99", "location": [-283.7147216796875, -2.0], "speed": [-19.606017774253818, 0.0, 0], "yaw": -179.99996948242188}, "Sensor_Information_Container": [0, 1, 2, 3], "Perceived_Object_Container": [{"time": 120.60000001043082, "location": {"x": -168.57822214043455, "y": -2.684651191107162}, "speed": {"x": -16.56249975319952, "y": 0.0, "z": 0}, "pseudonym": 7}, {"time": 120.60000001043082, "location": {"x": -370.92703902503104, "y": 5.214697674357313}, "speed": {"x": 16.280517335526387, "y": 0.0, "z": 0}, "pseudonym": 9}], "option": {"size": 331, "type": "CPM"}}
{"timestamp": 120.70000001192093, "ITS_PDU_Header": {"tmp": "tmp"}, "Basic_Container": {"tmp": "tmp"}, "HF_Container": {"sumo_id": "99", "location": [-285.6668701171875, -2.0], "speed": [-19.521484084107218, 0.0, 0], "yaw": -179.99996948242188}, "LF_Container": {"tmp": "tmp"}, "Special_Vehicle_Container": {"tmp": "tmp"}, "option": {"size": 190, "type": "CAM"}}
{"timestamp": 120.80000001341105, "ITS_PDU_Header": {"tmp": "tmp"}, "Management_Container": {"tmp": "tmp"}, "Station_Data_Container": {"sumo_id": "99", "location": [-287.62298583984375, -2.0], "speed": [-19.561156935078547, 0.0, 0], "yaw": -179.99996948242188}, "Sensor_Information_Container": [0, 1, 2, 3], "Perceived_Object_Container": [{"time": 120.80000001341105, "location": {"x": -302.4916900354135, "y": 5.467574484819353}, "speed": {"x": 5.208740156758723, "y": 0.0, "z": 0}, "pseudonym": 2}, {"time": 120.80000001341105, "location": {"x": -171.69637092192255, "y": -9.834824818433361}, "speed": {"x": -14.746703881819489, "y": 0.0, "z": 0}, "pseudonym": 10}, {"time": 120.80000001341105, "location": {"x": -250.53034020671026, "y": -5.023233470140857}, "speed": {"x": -15.566406018042475, "y": 0.0, "z": 0}, "pseudonym": 11}], "option": {"size": 366, "type": "CPM"}}
{"timestamp": 120.90000001490117, "ITS_PDU_Header": {"tmp": "tmp"}, "Management_Container": {"tmp": "tmp"}, "Station_Data_Container": {"sumo_id": "99", "location": [-289.5733642578125, -2.0], "speed": [-19.50378388905847, 0.0, 0], "yaw": -179.99996948242188}, "Sensor_Information_Container": [0, 1, 2, 3], "Perceived_Object_Container": [{"time": 120.90000001490117, "location": {"x": -337.96855263218777, "y": 8.882906659006844}, "speed": {"x": 15.626830821829575, "y": 0.0, "z": 0}, "pseudonym": 12}], "option": {"size": 296, "type": "CPM"}}
{"timestamp": 121.00000001639128, "ITS_PDU_Header": {"tmp": "tmp"}, "Management_Container": {"tmp": "tmp"}, "Station_Data_Container": {"sumo_id": "99", "location": [-291.53424072265625, -2.0], "speed": [-19.60876435624414, 0.0, 0], "yaw": -179.99996948242188}, "Sensor_Information_Container": [0, 1, 2, 3], "Perceived_Object_Container": [{"time": 121.00000001639128, "location": {"x": -434.1069817974028, "y": 8.638826268212366}, "speed": {"x": 16.15631079440846, "y": 0.0, "z": 0}, "pseudonym": 13}], "option": {"size": 296, "type": "CPM"}}
{"timestamp": 121.00000001639128, "ITS_PDU_Header": {"tmp": "tmp"}, "Basic_Container": {"tmp": "tmp"}, "HF_Container": {"sumo_id": "99", "location": [-291.53424072265625, -2.0], "speed": [-19.60876435624414, 0.0, 0], "yaw": -179.99996948242188}, "LF_Container": {"tmp": "tmp"}, "Special_Vehicle_Container": {"tmp": "tmp"}, "option": {"size": 190, "type": "CAM"}}
{"timestamp": 121.1000000178814, "ITS_PDU_Header": {"tmp": "tmp"}, "Management_Container": {"tmp": "tmp"}, "Station_Data_Container": {"sumo_id": "99", "location": [-293.49237060546875, -2.0], "speed": [-19.581298536340913, 0.0, 0], "yaw": -179.99996948242188}, "Sensor_Information_Container": [0, 1, 2, 3], "Perceived_Object_Container": [{"time": 121.1000000178814, "location": {"x": -300.46882569302244, "y": 6.093860675417248}, "speed": {"x": 5.768432531231157, "y": 0.0, "z": 0}, "pseudonym": 14}], "option": {"size": 296, "type": "CPM"}}
{"timestamp": 121.20000001937152, "ITS_PDU_Header": {"tmp": "tmp"}, "Management_Container": {"tmp": "tmp"}, "Station_Data_Container": {"sumo_id": "99", "location": [-295.44512939453125, -2.0], "speed": [-19.52758759964127, 0.0, 0], "yaw": -179.99996948242188}, "Sensor_Information_Container": [0, 1, 2, 3], "Perceived_Object_Container": [{"time": 121.20000001937152, "location": {"x": -293.64471272656846, "y": -9.246643267197282}, "speed": {"x": -17.266235094275547, "y": 0.0, "z": 0}, "pseudonym": 0}, {"time": 121.20000001937152, "location": {"x": -233.89978954904316, "y": 8.998430621210018}, "speed": {"x": 19.345702836726563, "y": 0.0, "z": 0}, "pseudonym": 5}, {"time": 121.20000001937152, "location": {"x": -324.7336385583221, "y": 1.880009400375951}, "speed": {"x": -3247.8789799231445, "y": 19.99999970197678, "z": 0}, "pseudonym": 15}, {"time": 121.20000001937152, "location": {"x": -420.82246408782726, "y": -1.9569578813074153}, "speed": {"x": -18.21228000205338, "y": 0.0, "z": 0}, "pseudonym": 1}, {"time": 121.20000001937152, "location": {"x": -333.1607830696715, "y": 9.175493149161102}, "speed": {"x": 16.285094972176925, "y": 0.0, "z": 0}, "pseudonym": 12}, {"time": 121.20000001937152, "location": {"x": -405.2527063715984, "y": -5.358044193447004}, "speed": {"x": -17.242126207916048, "y": 0.0, "z": 0}, "pseudonym": 3}], "option": {"size": 471, "type": "CPM"}}
{"timestamp": 121.30000002086163, "ITS_PDU_Header": {"tmp": "tmp"}, "Management_Container": {"tmp": "tmp"}, "Station_Data_Container": {"sumo_id": "99", "location": [-297.40350341796875, -5.75], "speed": [-19.583739942554534, -37.49999944120646, 0], "yaw": -179.99996948242188}, "Sensor_Information_Container": [0, 1, 2, 3], "Perceived_Object_Container": [{"time": 121.30000002086163, "location": {"x": -324.4069849448532, "y": 1.8502860886486971}, "speed": {"x": 0.24902343378926167, "y": 0.0, "z": 0}, "pseudonym": 16}, {"time": 121.30000002086163, "location": {"x": -300.356293867925, "y": 5.077716190725964}, "speed": {"x": 6.134033111720784, "y": 0.0, "z": 0}, "pseudonym": 2}], "option": {"size": 331, "type": "CPM"}}
{"timestamp": 121.30000002086163, "ITS_PDU_Header": {"tmp": "tmp"}, "Basic_Container": {"tmp": "tmp"}, "HF_Container": {"sumo_id": "99", "location": [-297.40350341796875, -5.75], "speed": [-19.583739942554534, -37.49999944120646, 0], "yaw": -179.99996948242188}, "LF_Container": {"tmp": "tmp"}, "Special_Vehicle_Container": {"tmp": "tmp"}, "option": {"size": 190, "type": "CAM"}}
{"timestamp": 121.40000002235175, "ITS_PDU_Header": {"tmp": "tmp"}, "Basic_Container": {"tmp": "tmp"}, "HF_Container": {"sumo_id": "99", "location": [-299.35516357421875, -2.0], "speed": [-19.516601271679978, 37.49999944120646, 0], "yaw": -179.99996948242188}, "LF_Container": {"tmp": "tmp"}, "Special_Vehicle_Container": {"tmp": "tmp"}, "option": {"size": 190, "type": "CAM"}}
{"timestamp": 121.50000002384186, "ITS_PDU_Header": {"tmp": "tmp"}, "Management_Container": {"tmp": "tmp"}, "Station_Data_Container": {"sumo_id": "99", "location": [-301.31048583984375, -2.0], "speed": [-19.55322236488428, 0.0, 0], "yaw": -179.99996948242188}, "Sensor_Information_Container": [0, 1, 2, 3], "Perceived_Object_Container": [{"time": 121.50000002384186, "location": {"x": -426.214324035107, "y": -2.1903862429573864}, "speed": {"x": -17.382812240975912, "y": 0.0, "z": 0}, "pseudonym": 1}], "option": {"size": 296, "type": "CPM"}}
{"timestamp": 121.50000002384186, "ITS_PDU_Header": {"tmp": "tmp"}, "Basic_Container": {"tmp": "tmp"}, "HF_Container": {"sumo_id": "99", "location": [-301.31048583984375, -2.0], "speed": [-19.55322236488428, 0.0, 0], "yaw": -179.99996948242188}, "LF_Container": {"tmp": "tmp"}, "Special_Vehicle_Container": {"tmp": "tmp"}, "option": {"size": 190, "type": "CAM"}}
{"timestamp": 121.60000002533198, "ITS_PDU_Header": {"tmp": "tmp"}, "Management_Container": {"tmp": "tmp"}, "Station_Data_Container": {"sumo_id": "99", "location": [-303.26715087890625, -2.0], "speed": [-19.566650099059192, 0.0, 0], "yaw": -179.99996948242188}, "Sensor_Information_Container": [0, 1, 2, 3], "Perceived_Object_Container": [{"time": 121.60000002533198, "location": {"x": -324.01403235242924, "y": 2.0132645807065095}, "speed": {"x": 0.9637451028265789, "y": 0.0, "z": 0}, "pseudonym": 16}, {"time": 121.60000002533198, "location": {"x": -299.3961941815535, "y": 5.369266734904668}, "speed": {"x": 6.738281149591787, "y": 0.0, "z": 0}, "pseudonym": 2}, {"time": 121.60000002533198, "location": {"x": -299.7254012332783, "y": 5.457811224451606}, "speed": {"x": 6.738281149591787, "y": 0.0, "z": 0}, "pseudonym": 2}], "option": {"size": 366, "type": "CPM"}}
{"timestamp": 121.7000000268221, "ITS_PDU_Header": {"tmp": "tmp"}, "Management_Container": {"tmp": "tmp"}, "Station_Data_Container": {"sumo_id": "99", "location": [-305.21759033203125, -2.0], "speed": [-19.504394240611877, 0.0, 0], "yaw": -179.99996948242188}, "Sensor_Information_Container": [0, 1, 2, 3], "Perceived_Object_Container": [{"time": 121.7000000268221, "location": {"x": -429.504771491849, "y": -1.8882765943757889}, "speed": {"x": -16.483154051256864, "y": 0.0, "z": 0}, "pseudonym": 1}], "option": {"size": 296, "type": "CPM"}}
{"timestamp": 121.80000002831221, "ITS_PDU_Header": {"tmp": "tmp"}, "Management_Container": {"tmp": "tmp"}, "Station_Data_Container": {"sumo_id": "99", "location": [-307.17401123046875, -2.0], "speed": [-19.564208692845572, 0.0, 0], "yaw": -179.99996948242188}, "Sensor_Information_Container": [0, 1, 2, 3], "Perceived_Object_Container": [{"time": 121.80000002831221, "location": {"x": -406.9406734887426, "y": -2.067221011455663}, "speed": {"x": -16.655883540870494, "y": 0.0, "z": 0}, "pseudonym": 17}, {"time": 121.80000002831221, "location": {"x": -415.4381416390648, "y": -5.597005854556204}, "speed": {"x": -16.738281000580177, "y": 0.0, "z": 0}, "pseudonym": 3}, {"time": 121.80000002831221, "location": {"x": -296.3539386095707, "y": 5.031291396653915}, "speed": {"x": 7.133788956198261, "y": 0.0, "z": 0}, "pseudonym": 14}], "option": {"size": 366, "type": "CPM"}}
{"timestamp": 121.80000002831221, "ITS_PDU_Header": {"tmp": "tmp"}, "Basic_Container": {"tmp": "tmp"}, "HF_Container": {"sumo_id": "99", "location": [-307.17401123046875, -2.0], "speed": [-19.564208692845572, 0.0, 0], "yaw": -179.99996948242188}, "LF_Container": {"tmp": "tmp"}, "Special_Vehicle_Container": {"tmp": "tmp"}, "option": {"size": 190, "type": "CAM"}}
{"timestamp": 121.90000002980233, "ITS_PDU_Header": {"tmp": "tmp"}, "Management_Container": {"tmp": "tmp"}, "Station_Data_Container": {"sumo_id": "99", "location": [-309.12738037109375, -2.0], "speed": [-19.53369111517532, 0.0, 0], "yaw": -179.99996948242188}, "Sensor_Information_Container": [0, 1, 2, 3], "Perceived_Object_Container": [{"time": 121.90000002980233, "location": {"x": -323.58447310684545, "y": 1.8039078410521947}, "speed": {"x": 1.7126464588545791, "y": 0.0, "z": 0}, "pseudonym": 16}, {"time": 121.90000002980233, "location": {"x": -432.4494094107599, "y": -2.130049077606901}, "speed": {"x": -15.583495861537816, "y": 0.0, "z": 0}, "pseudonym": 1}, {"time": 121.90000002980233, "location": {"x": -296.6533378160983, "y": 5.015867412736056}, "speed": {"x": 7.319335828433397, "y": 0.0, "z": 0}, "pseudonym": 2}], "option": {"size": 366, "type": "CPM"}}
{"timestamp": 122.00000003129244, "ITS_PDU_Header": {"tmp": "tmp"}, "Management_Container": {"tmp": "tmp"}, "Station_Data_Container": {"sumo_id": "99", "location": [-311.0843505859375, -2.0], "speed": [-19.569701856826217, 0.0, 0], "yaw": -179.99996948242188}, "Sensor_Information_Container": [0, 1, 2, 3], "Perceived_Object_Container": [{"time": 122.00000003129244, "location": {"x": -347.4085316879304, "y": 5.212526227403772}, "speed": {"x": 16.492614500334643, "y": 0.0, "z": 0}, "pseudonym": 9}, {"time": 122.00000003129244, "location": {"x": -418.02402135718387, "y": 8.640579420069521}, "speed": {"x": 16.09619116639806, "y": 0.0, "z": 0}, "pseudonym": 13}], "option": {"size": 331, "type": "CPM"}}
{"timestamp": 122.10000003278256, "ITS_PDU_Header": {"tmp": "tmp"}, "Management_Container": {"tmp": "tmp"}, "Station_Data_Container": {"sumo_id": "99", "location": [-313.03826904296875, -2.0], "speed": [-19.539184279155965, 0.0, 0], "yaw": -179.99996948242188}, "Sensor_Information_Container": [0, 1, 2, 3], "Perceived_Object_Container": [{"time": 122.10000003278256, "location": {"x": -420.284852600242, "y": -5.965231165840452}, "speed": {"x": -16.155700442855053, "y": 0.0, "z": 0}, "pseudonym": 3}, {"time": 122.10000003278256, "location": {"x": -435.25297082397447, "y": -1.9384415197151283}, "speed": {"x": -14.683227320265363, "y": 0.0, "z": 0}, "pseudonym": 1}], "option": {"size": 331, "type": "CPM"}}
{"timestamp": 122.10000003278256, "ITS_PDU_Header": {"tmp": "tmp"}, "Basic_Container": {"tmp": "tmp"}, "HF_Container": {"sumo_id": "99", "location": [-313.03826904296875, -2.0], "speed": [-19.539184279155965, 0.0, 0], "yaw": -179.99996948242188}, "LF_Container": {"tmp": "tmp"}, "Special_Vehicle_Container": {"tmp": "tmp"}, "option": {"size": 190, "type": "CAM"}}
{"timestamp": 122.20000003427268, "ITS_PDU_Header": {"tmp": "tmp"}, "Management_Container": {"tmp": "tmp"}, "Station_Data_Container": {"sumo_id": "99", "location": [-314.99298095703125, -2.0], "speed": [-19.54711884935023, 0.0, 0], "yaw": -179.99996948242188}, "Sensor_Information_Container": [0, 1, 2, 3], "Perceived_Object_Container": [{"time": 122.20000003427268, "location": {"x": -310.97406954846093, "y": -9.243566555082314}, "speed": {"x": -17.331542710489888, "y": 0.0, "z": 0}, "pseudonym": 0}, {"time": 122.20000003427268, "location": {"x": -323.23136545746235, "y": 1.5101387833197064}, "speed": {"x": 2.354736293036695, "y": 0.0, "z": 0}, "pseudonym": 16}, {"time": 122.20000003427268, "location": {"x": -295.0588737131863, "y": 5.559306463139115}, "speed": {"x": 7.931518436498665, "y": 0.0, "z": 0}, "pseudonym": 2}, {"time": 122.20000003427268, "location": {"x": -214.8174930749309, "y": 9.081681989078612}, "speed": {"x": 19.388427445464917, "y": 0.0, "z": 0}, "pseudonym": 5}, {"time": 122.20000003427268, "location": {"x": -197.4479977148569, "y": -2.7060268678832564}, "speed": {"x": -19.552459425442525, "y": 0.0, "z": 0}, "pseudonym": 18}, {"time": 122.20000003427268, "location": {"x": -317.2783236508061, "y": 8.667299223179104}, "speed": {"x": 16.577148190481243, "y": 0.0, "z": 0}, "pseudonym": 12}], "option": {"size": 471, "type": "CPM"}}
{"timestamp": 122.30000003576279, "ITS_PDU_Header": {"tmp": "tmp"}, "Management_Container": {"tmp": "tmp"}, "Station_Data_Container": {"sumo_id": "99", "location": [-316.9527587890625, -2.0], "speed": [-19.59777802828285, 0.0, 0], "yaw": -179.99996948242188}, "Sensor_Information_Container": [0, 1, 2, 3], "Perceived_Object_Container": [{"time": 122.30000003576279, "location": {"x": -193.68680893276775, "y": -8.652271824348983}, "speed": {"x": -14.702300806309271, "y": 0.0, "z": 0}, "pseudonym": 10}], "option": {"size": 296, "type": "CPM"}}
{"timestamp": 122.40000003725291, "ITS_PDU_Header": {"tmp": "tmp"}, "Management_Container": {"tmp": "tmp"}, "Station_Data_Container": {"sumo_id": "99", "location": [-318.907958984375, -2.0], "speed": [-19.55200166177747, 0.0, 0], "yaw": -179.99996948242188}, "Sensor_Information_Container": [0, 1, 2, 3], "Perceived_Object_Container": [{"time": 122.40000003725291, "location": {"x": -291.55871913522867, "y": 5.026098761860825}, "speed": {"x": 8.20739733863775, "y": 0.0, "z": 0}, "pseudonym": 14}, {"time": 122.40000003725291, "location": {"x": -322.19778197999847, "y": 2.3534470166017374}, "speed": {"x": 2.861938433916294, "y": 0.0, "z": 0}, "pseudonym": 16}], "option": {"size": 331, "type": "CPM"}}
{"timestamp": 122.40000003725291, "ITS_PDU_Header": {"tmp": "tmp"}, "Basic_Container": {"tmp": "tmp"}, "HF_Container": {"sumo_id": "99", "location": [-318.907958984375, -2.0], "speed": [-19.55200166177747, 0.0, 0], "yaw": -179.99996948242188}, "LF_Container": {"tmp": "tmp"}, "Special_Vehicle_Container": {"tmp": "tmp"}, "option": {"size": 190, "type": "CAM"}}
{"timestamp": 122.50000003874302, "ITS_PDU_Header": {"tmp": "tmp"}, "Management_Container": {"tmp": "tmp"}, "Station_Data_Container": {"sumo_id": "99", "location": [-320.86328125, -2.0], "speed": [-19.55322236488428, 0.0, 0], "yaw": -179.99996948242188}, "Sensor_Information_Container": [0, 1, 2, 3], "Perceived_Object_Container": [{"time": 122.50000003874302, "location": {"x": -293.1562996679036, "y": 5.786204496749966}, "speed": {"x": 8.433227413397619, "y": 0.0, "z": 0}, "pseudonym": 2}, {"time": 122.50000003874302, "location": {"x": -426.4752706252358, "y": -5.451547130484171}, "speed": {"x": -15.377197036486908, "y": 0.0, "z": 0}, "pseudonym": 3}], "option": {"size": 331, "type": "CPM"}}
{"timestamp": 122.60000004023314, "ITS_PDU_Header": {"tmp": "tmp"}, "Management_Container": {"tmp": "tmp"}, "Station_Data_Container": {"sumo_id": "99", "location": [-322.8211669921875, -2.0], "speed": [-19.578857130127293, 0.0, 0], "yaw": -179.99996948242188}, "Sensor_Information_Container": [0, 1, 2, 3], "Perceived_Object_Container": [{"time": 122.60000004023314, "location": {"x": -442.4431664101048, "y": -2.4259288611619345}, "speed": {"x": -14.137878207297948, "y": 0.0, "z": 0}, "pseudonym": 1}], "option": {"size": 296, "type": "CPM"}}
{"timestamp": 122.70000004172326, "ITS_PDU_Header": {"tmp": "tmp"}, "Basic_Container": {"tmp": "tmp"}, "HF_Container": {"sumo_id": "99", "location": [-324.7789306640625, -2.0], "speed": [-19.577636427020483, 0.0, 0], "yaw": -179.99996948242188}, "LF_Container": {"tmp": "tmp"}, "Special_Vehicle_Container": {"tmp": "tmp"}, "option": {"size": 190, "type": "CAM"}}
{"timestamp": 122.80000004321337, "ITS_PDU_Header": {"tmp": "tmp"}, "Management_Container": {"tmp": "tmp"}, "Station_Data_Container": {"sumo_id": "99", "location": [-326.7364501953125, -2.0], "speed": [-19.575195020806863, 0.0, 0], "yaw": -179.99996948242188}, "Sensor_Information_Container": [0, 1, 2, 3], "Perceived_Object_Container": [{"time": 122.80000004321337, "location": {"x": -287.6036412338441, "y": 4.937129526658802}, "speed": {"x": 8.9019774064127, "y": 0.0, "z": 0}, "pseudonym": 14}, {"time": 122.80000004321337, "location": {"x": -430.91365852194593, "y": -6.17546552254706}, "speed": {"x": -14.794311302985083, "y": 0.0, "z": 0}, "pseudonym": 3}], "option": {"size": 331, "type": "CPM"}}
{"timestamp": 122.90000004470349, "ITS_PDU_Header": {"tmp": "tmp"}, "Management_Container": {"tmp": "tmp"}, "Station_Data_Container": {"sumo_id": "99", "location": [-328.6918640136719, -2.0], "speed": [-19.55413789221439, 0.0, 0], "yaw": -179.99996948242188}, "Sensor_Information_Container": [0, 1, 2, 3], "Perceived_Object_Container": [{"time": 122.90000004470349, "location": {"x": -321.69857532665566, "y": 1.4778196509107564}, "speed": {"x": 3.779907170237494, "y": 0.0, "z": 0}, "pseudonym": 16}], "option": {"size": 296, "type": "CPM"}}
{"timestamp": 123.0000000461936, "ITS_PDU_Header": {"tmp": "tmp"}, "Management_Container": {"tmp": "tmp"}, "Station_Data_Container": {"sumo_id": "99", "location": [-330.6466979980469, -2.0], "speed": [-19.54833955245704, 0.0, 0], "yaw": -179.99996948242188}, "Sensor_Information_Container": [0, 1, 2, 3], "Perceived_Object_Container": [{"time": 123.0000000461936, "location": {"x": -288.5132456045155, "y": 5.811337238625377}, "speed": {"x": 9.288329939718098, "y": 0.0, "z": 0}, "pseudonym": 2}, {"time": 123.0000000461936, "location": {"x": -330.72896158341325, "y": 5.224313844465851}, "speed": {"x": 16.42578100523679, "y": 0.0, "z": 0}, "pseudonym": 9}], "option": {"size": 331, "type": "CPM"}}
{"timestamp": 123.0000000461936, "ITS_PDU_Header": {"tmp": "tmp"}, "Basic_Container": {"tmp": "tmp"}, "HF_Container": {"sumo_id": "99", "location": [-330.6466979980469, -2.0], "speed": [-19.54833955245704, 0.0, 0], "yaw": -179.99996948242188}, "LF_Container": {"tmp": "tmp"}, "Special_Vehicle_Container": {"tmp": "tmp"}, "option": {"size": 190, "type": "CAM"}}
{"timestamp": 123.10000004768372, "ITS_PDU_Header": {"tmp": "tmp"}, "Management_Container": {"tmp": "tmp"}, "Station_Data_Container": {"sumo_id": "99", "location": [-332.6004943847656, -2.0], "speed": [-19.537963576049155, 0.0, 0], "yaw": -179.99996948242188}, "Sensor_Information_Container": [0, 1, 2, 3], "Perceived_Object_Container": [{"time": 123.10000004768372, "location": {"x": -435.17650114305064, "y": -5.458286797739885}, "speed": {"x": -14.211120393706555, "y": 0.0, "z": 0}, "pseudonym": 3}], "option": {"size": 296, "type": "CPM"}}
{"timestamp": 123.20000004917384, "ITS_PDU_Header": {"tmp": "tmp"}, "Management_Container": {"tmp": "tmp"}, "Station_Data_Container": {"sumo_id": "99", "location": [-334.5607604980469, -2.0], "speed": [-19.60266084071009, 0.0, 0], "yaw": -179.99996948242188}, "Sensor_Information_Container": [0, 1, 2, 3], "Perceived_Object_Container": [{"time": 123.20000004917384, "location": {"x": -320.62344963879076, "y": 1.6324491846954823}, "speed": {"x": 4.354247981991649, "y": 0.0, "z": 0}, "pseudonym": 16}, {"time": 123.20000004917384, "location": {"x": -195.43581809234155, "y": 9.389921762743937}, "speed": {"x": 19.36691255320739, "y": 0.0, "z": 0}, "pseudonym": 5}, {"time": 123.20000004917384, "location": {"x": -217.20549269293178, "y": -1.3028231269094603}, "speed": {"x": -19.511718459252737, "y": 0.0, "z": 0}, "pseudonym": 18}], "option": {"size": 366, "type": "CPM"}}
{"timestamp": 123.30000005066395, "ITS_PDU_Header": {"tmp": "tmp"}, "Management_Container": {"tmp": "tmp"}, "Station_Data_Container": {"sumo_id": "99", "location": [-336.5180358886719, -2.0], "speed": [-19.572753614593243, 0.0, 0], "yaw": -179.99996948242188}, "Sensor_Information_Container": [0, 1, 2, 3], "Perceived_Object_Container": [{"time": 123.30000005066395, "location": {"x": -285.3692833557494, "y": 5.749666218616559}, "speed": {"x": 9.832763525355405, "y": 0.0, "z": 0}, "pseudonym": 2}, {"time": 123.30000005066395, "location": {"x": -300.25185671579436, "y": 9.487522971439269}, "speed": {"x": 16.474609129509194, "y": 0.0, "z": 0}, "pseudonym": 12}, {"time": 123.30000005066395, "location": {"x": -208.434170836188, "y": -9.836444636971187}, "speed": {"x": -14.682006617158553, "y": 0.0, "z": 0}, "pseudonym": 10}], "option": {"size": 366, "type": "CPM"}}
{"timestamp": 123.30000005066395, "ITS_PDU_Header": {"tmp": "tmp"}, "Basic_Container": {"tmp": "tmp"}, "HF_Container": {"sumo_id": "99", "location": [-336.5180358886719, -2.0], "speed": [-19.572753614593243, 0.0, 0], "yaw": -179.99996948242188}, "LF_Container": {"tmp": "tmp"}, "Special_Vehicle_Container": {"tmp": "tmp"}, "option": {"size": 190, "type": "CAM"}}
{"timestamp": 123.40000005215407, "ITS_PDU_Header": {"tmp": "tmp"}, "Management_Container": {"tmp": "tmp"}, "Station_Data_Container": {"sumo_id": "99", "location": [-338.470703125, -2.0], "speed": [-19.52667207231116, 0.0, 0], "yaw": -179.99996948242188}, "Sensor_Information_Container": [0, 1, 2, 3], "Perceived_Object_Container": [{"time": 123.40000005215407, "location": {"x": -439.26523106735203, "y": -5.767895047193565}, "speed": {"x": -13.627013957097919, "y": 0.0, "z": 0}, "pseudonym": 3}, {"time": 123.40000005215407, "location": {"x": -282.1185167750689, "y": 5.026761076919058}, "speed": {"x": 10.020141452250757, "y": 0.0, "z": 0}, "pseudonym": 14}], "option": {"size": 331, "type": "CPM"}}
{"timestamp": 123.50000005364419, "ITS_PDU_Header": {"tmp": "tmp"}, "Management_Container": {"tmp": "tmp"}, "Station_Data_Container": {"sumo_id": "99", "location": [-340.42144775390625, -2.0], "speed": [-19.507445998378902, 0.0, 0], "yaw": -179.99996948242188}, "Sensor_Information_Container": [0, 1, 2, 3], "Perceived_Object_Container": [{"time": 123.50000005364419, "location": {"x": -319.42653246611457, "y": 1.8539792445891075}, "speed": {"x": 4.88586418500745, "y": 0.0, "z": 0}, "pseudonym": 16}, {"time": 123.50000005364419, "location": {"x": -455.6432654222315, "y": -1.783869552226571}, "speed": {"x": -14.692992945119844, "y": 0.0, "z": 0}, "pseudonym": 1}, {"time": 123.50000005364419, "location": {"x": -392.93902884673275, "y": 9.06979781598498}, "speed": {"x": 16.094665287514548, "y": 0.0, "z": 0}, "pseudonym": 13}, {"time": 123.50000005364419, "location": {"x": -442.4228968116894, "y": -6.550104360838358}, "speed": {"x": -13.433532514668517, "y": 0.0, "z": 0}, "pseudonym": 19}], "option": {"size": 401, "type": "CPM"}}
{"timestamp": 123.6000000551343, "ITS_PDU_Header": {"tmp": "tmp"}, "Management_Container": {"tmp": "tmp"}, "Station_Data_Container": {"sumo_id": "99", "location": [-342.3751220703125, -2.0], "speed": [-19.536742872942344, 0.0, 0], "yaw": -179.99996948242188}, "Sensor_Information_Container": [0, 1, 2, 3], "Perceived_Object_Container": [{"time": 123.6000000551343, "location": {"x": -282.37085047843595, "y": 5.628281241685636}, "speed": {"x": 10.42510970793501, "y": 0.0, "z": 0}, "pseudonym": 2}], "option": {"size": 296, "type": "CPM"}}
{"timestamp": 123.6000000551343, "ITS_PDU_Header": {"tmp": "tmp"}, "Basic_Container": {"tmp": "tmp"}, "HF_Container": {"sumo_id": "99", "location": [-342.3751220703125, -2.0], "speed": [-19.536742872942344, 0.0, 0], "yaw": -179.99996948242188}, "LF_Container": {"tmp": "tmp"}, "Special_Vehicle_Container": {"tmp": "tmp"}, "option": {"size": 190, "type": "CAM"}}
{"timestamp": 123.70000005662442, "ITS_PDU_Header": {"tmp": "tmp"}, "Management_Container": {"tmp": "tmp"}, "Station_Data_Container": {"sumo_id": "99", "location": [-344.33343505859375, -2.0], "speed": [-19.58312959100113, 0.0, 0], "yaw": -179.99996948242188}, "Sensor_Information_Container": [0, 1, 2, 3], "Perceived_Object_Container": [{"time": 123.70000005662442, "location": {"x": -443.19821356024374, "y": -1.9762804214002943}, "speed": {"x": -13.04382304781939, "y": 37.49999944120646, "z": 0}, "pseudonym": 20}, {"time": 123.70000005662442, "location": {"x": -430.91099829361184, "y": -2.05810615156592}, "speed": {"x": -11.024169757602069, "y": 0.0, "z": 0}, "pseudonym": 21}], "option": {"size": 331, "type": "CPM"}}
{"timestamp": 123.80000005811453, "ITS_PDU_Header": {"tmp": "tmp"}, "Management_Container": {"tmp": "tmp"}, "Station_Data_Container": {"sumo_id": "99", "location": [-346.28582763671875, -2.0], "speed": [-19.52392549032084, 0.0, 0], "yaw": -179.99996948242188}, "Sensor_Information_Container": [0, 1, 2, 3], "Perceived_Object_Container": [{"time": 123.80000005811453, "location": {"x": -444.51795246828755, "y": -2.138466788988956}, "speed": {"x": -13.045654102479606, "y": 0.0, "z": 0}, "pseudonym": 22}, {"time": 123.80000005811453, "location": {"x": -317.8427944165257, "y": 1.856170881612646}, "speed": {"x": 5.480956949577377, "y": 0.0, "z": 0}, "pseudonym": 16}], "option": {"size": 331, "type": "CPM"}}
{"timestamp": 123.90000005960465, "ITS_PDU_Header": {"tmp": "tmp"}, "Management_Container": {"tmp": "tmp"}, "Station_Data_Container": {"sumo_id": "99", "location": [-348.2381591796875, -2.0], "speed": [-19.523315138767433, 0.0, 0], "yaw": -179.99996948242188}, "Sensor_Information_Container": [0, 1, 2, 3], "Perceived_Object_Container": [{"time": 123.90000005960465, "location": {"x": -278.22668843873373, "y": 5.067352823460691}, "speed": {"x": 11.082153155175549, "y": 0.0, "z": 0}, "pseudonym": 2}, {"time": 123.90000005960465, "location": {"x": -447.68712323160565, "y": -2.7829554799967724}, "speed": {"x": -13.205261033695027, "y": 0.0, "z": 0}, "pseudonym": 23}], "option": {"size": 331, "type": "CPM"}}
{"timestamp": 123.90000005960465, "ITS_PDU_Header": {"tmp": "tmp"}, "Basic_Container": {"tmp": "tmp"}, "HF_Container": {"sumo_id": "99", "location": [-348.2381591796875, -2.0], "speed": [-19.523315138767433, 0.0, 0], "yaw": -179.99996948242188}, "LF_Container": {"tmp": "tmp"}, "Special_Vehicle_Container": {"tmp": "tmp"}, "option": {"size": 190, "type": "CAM"}}
{"timestamp": 124.00000006109477, "ITS_PDU_Header": {"tmp": "tmp"}, "Management_Container": {"tmp": "tmp"}, "Station_Data_Container": {"sumo_id": "99", "location": [-350.1916198730469, -2.0], "speed": [-19.534606642505427, 0.0, 0], "yaw": -179.99996948242188}, "Sensor_Information_Container": [0, 1, 2, 3], "Perceived_Object_Container": [{"time": 124.00000006109477, "location": {"x": -314.65046659431414, "y": 5.563973362470115}, "speed": {"x": 16.26159643737083, "y": 0.0, "z": 0}, "pseudonym": 9}], "option": {"size": 296, "type": "CPM"}}
{"timestamp": 124.10000006258488, "ITS_PDU_Header": {"tmp": "tmp"}, "Management_Container": {"tmp": "tmp"}, "Station_Data_Container": {"sumo_id": "99", "location": [-352.14495849609375, -2.0], "speed": [-19.533385939398617, 0.0, 0], "yaw": -179.99996948242188}, "Sensor_Information_Container": [0, 1, 2, 3], "Perceived_Object_Container": [{"time": 124.10000006258488, "location": {"x": -316.0128379086726, "y": 2.0852093322555945}, "speed": {"x": 6.070556550166659, "y": 0.0, "z": 0}, "pseudonym": 16}], "option": {"size": 296, "type": "CPM"}}
{"timestamp": 124.200000064075, "ITS_PDU_Header": {"tmp": "tmp"}, "Management_Container": {"tmp": "tmp"}, "Station_Data_Container": {"sumo_id": "99", "location": [-354.0978698730469, -2.0], "speed": [-19.52911347852478, 0.0, 0], "yaw": -179.99996948242188}, "Sensor_Information_Container": [0, 1, 2, 3], "Perceived_Object_Container": [{"time": 124.200000064075, "location": {"x": -237.63019461621764, "y": -1.7527208731535944}, "speed": {"x": -19.59060639753034, "y": 0.0, "z": 0}, "pseudonym": 18}, {"time": 124.200000064075, "location": {"x": -306.16192278993003, "y": -5.5464774624825965}, "speed": {"x": -15.581664806877601, "y": 0.0, "z": 0}, "pseudonym": 24}, {"time": 124.200000064075, "location": {"x": -420.0895805791997, "y": 2.2472000029450623}, "speed": {"x": 19.07379121968461, "y": 0.0, "z": 0}, "pseudonym": 25}], "option": {"size": 366, "type": "CPM"}}
{"timestamp": 124.200000064075, "ITS_PDU_Header": {"tmp": "tmp"}, "Basic_Container": {"tmp": "tmp"}, "HF_Container": {"sumo_id": "99", "location": [-354.0978698730469, -2.0], "speed": [-19.52911347852478, 0.0, 0], "yaw": -179.99996948242188}, "LF_Container": {"tmp": "tmp"}, "Special_Vehicle_Container": {"tmp": "tmp"}, "option": {"size": 190, "type": "CAM"}}
{"timestamp": 124.30000006556511, "ITS_PDU_Header": {"tmp": "tmp"}, "Management_Container": {"tmp": "tmp"}, "Station_Data_Container": {"sumo_id": "99", "location": [-356.0587158203125, -2.0], "speed": [-19.608459180467438, 0.0, 0], "yaw": -179.99996948242188}, "Sensor_Information_Container": [0, 1, 2, 3], "Perceived_Object_Container": [{"time": 124.30000006556511, "location": {"x": -283.2929137944709, "y": 8.618225597646143}, "speed": {"x": 16.484374754363674, "y": 0.0, "z": 0}, "pseudonym": 12}], "option": {"size": 296, "type": "CPM"}}
{"timestamp": 124.40000006705523, "ITS_PDU_Header": {"tmp": "tmp"}, "Management_Container": {"tmp": "tmp"}, "Station_Data_Container": {"sumo_id": "99", "location": [-358.01678466796875, -2.0], "speed": [-19.58068818478751, 0.0, 0], "yaw": -179.99996948242188}, "Sensor_Information_Container": [0, 1, 2, 3], "Perceived_Object_Container": [{"time": 124.40000006705523, "location": {"x": -452.5823090195494, "y": -2.099962451998574}, "speed": {"x": -13.626708781321216, "y": 0.0, "z": 0}, "pseudonym": 22}, {"time": 124.40000006705523, "location": {"x": -313.98733286737854, "y": 1.53838875787898}, "speed": {"x": 6.636352440173143, "y": 0.0, "z": 0}, "pseudonym": 16}], "option": {"size": 331, "type": "CPM"}}
{"timestamp": 124.50000006854535, "ITS_PDU_Header": {"tmp": "tmp"}, "Management_Container": {"tmp": "tmp"}, "Station_Data_Container": {"sumo_id": "99", "location": [-359.9708251953125, -2.0], "speed": [-19.540404982262775, 0.0, 0], "yaw": -179.99996948242188}, "Sensor_Information_Container": [0, 1, 2, 3], "Perceived_Object_Container": [{"time": 124.50000006854535, "location": {"x": -377.8443336848597, "y": 8.646076497091924}, "speed": {"x": 16.10321020926222, "y": 0.0, "z": 0}, "pseudonym": 13}], "option": {"size": 296, "type": "CPM"}}
{"timestamp": 124.50000006854535, "ITS_PDU_Header": {"tmp": "tmp"}, "Basic_Container": {"tmp": "tmp"}, "HF_Container": {"sumo_id": "99", "location": [-359.9708251953125, -2.0], "speed": [-19.540404982262775, 0.0, 0], "yaw": -179.99996948242188}, "LF_Container": {"tmp": "tmp"}, "Special_Vehicle_Container": {"tmp": "tmp"}, "option": {"size": 190, "type": "CAM"}}
{"timestamp": 124.60000007003546, "ITS_PDU_Header": {"tmp": "tmp"}, "Management_Container": {"tmp": "tmp"}, "Station_Data_Container": {"sumo_id": "99", "location": [-361.92578125, -2.0], "speed": [-19.54956025556385, 0.0, 0], "yaw": -179.99996948242188}, "Sensor_Information_Container": [0, 1, 2, 3], "Perceived_Object_Container": [{"time": 124.60000007003546, "location": {"x": -455.32481840730725, "y": -1.92323532912746}, "speed": {"x": -13.69842508884631, "y": 0.0, "z": 0}, "pseudonym": 17}, {"time": 124.60000007003546, "location": {"x": -441.3087661249796, "y": -2.0531340474364486}, "speed": {"x": -11.93145734173868, "y": 0.0, "z": 0}, "pseudonym": 21}], "option": {"size": 331, "type": "CPM"}}
{"timestamp": 124.70000007152558, "ITS_PDU_Header": {"tmp": "tmp"}, "Management_Container": {"tmp": "tmp"}, "Station_Data_Container": {"sumo_id": "99", "location": [-363.8859558105469, -2.0], "speed": [-19.601745313379983, 0.0, 0], "yaw": -179.99996948242188}, "Sensor_Information_Container": [0, 1, 2, 3], "Perceived_Object_Container": [{"time": 124.70000007152558, "location": {"x": -311.8629472621021, "y": 1.7584093617436813}, "speed": {"x": 7.203979384839842, "y": 0.0, "z": 0}, "pseudonym": 16}], "option": {"size": 296, "type": "CPM"}}
{"timestamp": 124.8000000730157, "ITS_PDU_Header": {"tmp": "tmp"}, "Management_Container": {"tmp": "tmp"}, "Station_Data_Container": {"sumo_id": "99", "location": [-365.83502197265625, -2.0], "speed": [-19.490661330660263, 0.0, 0], "yaw": -179.99996948242188}, "Sensor_Information_Container": [0, 1, 2, 3], "Perceived_Object_Container": [{"time": 124.8000000730157, "location": {"x": -267.793261270302, "y": 6.428831444700576}, "speed": {"x": 12.91809062781795, "y": 0.0, "z": 0}, "pseudonym": 2}], "option": {"size": 296, "type": "CPM"}}
{"timestamp": 124.8000000730157, "ITS_PDU_Header": {"tmp": "tmp"}, "Basic_Container": {"tmp": "tmp"}, "HF_Container": {"sumo_id": "99", "location": [-365.83502197265625, -2.0], "speed": [-19.490661330660263, 0.0, 0], "yaw": -179.99996948242188}, "LF_Container": {"tmp": "tmp"}, "Special_Vehicle_Container": {"tmp": "tmp"}, "option": {"size": 190, "type": "CAM"}}
{"timestamp": 125.00000007599593, "ITS_PDU_Header": {"tmp": "tmp"}, "Management_Container": {"tmp": "tmp"}, "Station_Data_Container": {"sumo_id": "99", "location": [-369.744873046875, -2.0], "speed": [-19.57855195435059, 0.0, 0], "yaw": -179.99996948242188}, "Sensor_Information_Container": [0, 1, 2, 3], "Perceived_Object_Container": [{"time": 125.00000007599593, "location": {"x": -298.4954354858826, "y": 5.705290958864387}, "speed": {"x": 16.519164792907763, "y": 0.0, "z": 0}, "pseudonym": 9}, {"time": 125.00000007599593, "location": {"x": -309.53302595992534, "y": 2.0201848958603783}, "speed": {"x": 7.789306524555288, "y": 0.0, "z": 0}, "pseudonym": 16}], "option": {"size": 331, "type": "CPM"}}
{"timestamp": 125.10000007748604, "ITS_PDU_Header": {"tmp": "tmp"}, "Management_Container": {"tmp": "tmp"}, "Station_Data_Container": {"sumo_id": "99", "location": [-371.6945495605469, -2.0], "speed": [-19.496764846194313, 0.0, 0], "yaw": -179.99996948242188}, "Sensor_Information_Container": [0, 1, 2, 3], "Perceived_Object_Container": [{"time": 125.10000007748604, "location": {"x": -264.08075606387183, "y": 6.16804540399489}, "speed": {"x": 13.55590800112623, "y": 0.0, "z": 0}, "pseudonym": 2}, {"time": 125.10000007748604, "location": {"x": -447.4606071986735, "y": -2.0506344236989076}, "speed": {"x": -12.536620906939792, "y": 0.0, "z": 0}, "pseudonym": 21}], "option": {"size": 331, "type": "CPM"}}
{"timestamp": 125.10000007748604, "ITS_PDU_Header": {"tmp": "tmp"}, "Basic_Container": {"tmp": "tmp"}, "HF_Container": {"sumo_id": "99", "location": [-371.6945495605469, -2.0], "speed": [-19.496764846194313, 0.0, 0], "yaw": -179.99996948242188}, "LF_Container": {"tmp": "tmp"}, "Special_Vehicle_Container": {"tmp": "tmp"}, "option": {"size": 190, "type": "CAM"}}
{"timestamp": 125.20000007897616, "ITS_PDU_Header": {"tmp": "tmp"}, "Management_Container": {"tmp": "tmp"}, "Station_Data_Container": {"sumo_id": "99", "location": [-373.652099609375, -2.0], "speed": [-19.575500196583565, 0.0, 0], "yaw": -179.99996948242188}, "Sensor_Information_Container": [0, 1, 2, 3], "Perceived_Object_Container": [{"time": 125.20000007897616, "location": {"x": -463.75025875804295, "y": -2.2682959530054854}, "speed": {"x": -14.244689729143833, "y": 0.0, "z": 0}, "pseudonym": 17}], "option": {"size": 296, "type": "CPM"}}
{"timestamp": 125.30000008046628, "ITS_PDU_Header": {"tmp": "tmp"}, "Management_Container": {"tmp": "tmp"}, "Station_Data_Container": {"sumo_id": "99", "location": [-375.60888671875, -2.0], "speed": [-19.567870802166002, 0.0, 0], "yaw": -179.99996948242188}, "Sensor_Information_Container": [0, 1, 2, 3], "Perceived_Object_Container": [{"time": 125.30000008046628, "location": {"x": -266.76899202850717, "y": 9.04819562563778}, "speed": {"x": 16.572265378054002, "y": 0.0, "z": 0}, "pseudonym": 12}, {"time": 125.30000008046628, "location": {"x": -306.9950788409976, "y": 1.9098347053815963}, "speed": {"x": 8.44909655378615, "y": 0.0, "z": 0}, "pseudonym": 16}], "option": {"size": 331, "type": "CPM"}}
{"timestamp": 125.40000008195639, "ITS_PDU_Header": {"tmp": "tmp"}, "Management_Container": {"tmp": "tmp"}, "Station_Data_Container": {"sumo_id": "99", "location": [-377.55914306640625, -2.0], "speed": [-19.50256318595166, 0.0, 0], "yaw": -179.99996948242188}, "Sensor_Information_Container": [0, 1, 2, 3], "Perceived_Object_Container": [{"time": 125.40000008195639, "location": {"x": -238.83203916523945, "y": -8.621958967664828}, "speed": {"x": -14.68032815038669, "y": 0.0, "z": 0}, "pseudonym": 10}, {"time": 125.40000008195639, "location": {"x": -398.46205345462084, "y": 1.4024638310271764}, "speed": {"x": 19.09179659051006, "y": 0.0, "z": 0}, "pseudonym": 25}], "option": {"size": 331, "type": "CPM"}}
{"timestamp": 125.40000008195639, "ITS_PDU_Header": {"tmp": "tmp"}, "Basic_Container": {"tmp": "tmp"}, "HF_Container": {"sumo_id": "99", "location": [-377.55914306640625, -2.0], "speed": [-19.50256318595166, 0.0, 0], "yaw": -179.99996948242188}, "LF_Container": {"tmp": "tmp"}, "Special_Vehicle_Container": {"tmp": "tmp"}, "option": {"size": 190, "type": "CAM"}}
{"timestamp": 125.50000008344651, "ITS_PDU_Header": {"tmp": "tmp"}, "Management_Container": {"tmp": "tmp"}, "Station_Data_Container": {"sumo_id": "99", "location": [-379.519287109375, -2.0], "speed": [-19.60144013760328, 0.0, 0], "yaw": -179.99996948242188}, "Sensor_Information_Container": [0, 1, 2, 3], "Perceived_Object_Container": [{"time": 125.50000008344651, "location": {"x": -262.2445298250934, "y": -2.6965220828962453}, "speed": {"x": -19.517821974786788, "y": 0.0, "z": 0}, "pseudonym": 18}, {"time": 125.50000008344651, "location": {"x": -361.8375300002143, "y": 8.773026045119199}, "speed": {"x": 16.08764624465039, "y": 0.0, "z": 0}, "pseudonym": 13}, {"time": 125.50000008344651, "location": {"x": -258.21348330499177, "y": 6.118147178908639}, "speed": {"x": 14.324340606863192, "y": 0.0, "z": 0}, "pseudonym": 2}, {"time": 125.50000008344651, "location": {"x": -290.0536084533689, "y": 1.7046032885953326}, "speed": {"x": 16.96838353621388, "y": 0.0, "z": 0}, "pseudonym": 26}], "option": {"size": 401, "type": "CPM"}}
{"timestamp": 125.60000008493662, "ITS_PDU_Header": {"tmp": "tmp"}, "Management_Container": {"tmp": "tmp"}, "Station_Data_Container": {"sumo_id": "99", "location": [-381.4686279296875, -2.0], "speed": [-19.493407912650586, 0.0, 0], "yaw": -179.99996948242188}, "Sensor_Information_Container": [0, 1, 2, 3], "Perceived_Object_Container": [{"time": 125.60000008493662, "location": {"x": -304.2435123177654, "y": 1.8469628122445623}, "speed": {"x": 9.178466660105189, "y": 0.0, "z": 0}, "pseudonym": 16}], "option": {"size": 296, "type": "CPM"}}
{"timestamp": 125.70000008642674, "ITS_PDU_Header": {"tmp": "tmp"}, "Management_Container": {"tmp": "tmp"}, "Station_Data_Container": {"sumo_id": "99", "location": [-383.4254150390625, -2.0], "speed": [-19.567870802166002, 0.0, 0], "yaw": -179.99996948242188}, "Sensor_Information_Container": [0, 1, 2, 3], "Perceived_Object_Container": [{"time": 125.70000008642674, "location": {"x": -286.5485661818954, "y": 2.018718512471577}, "speed": {"x": 17.478637434860506, "y": 0.0, "z": 0}, "pseudonym": 26}], "option": {"size": 296, "type": "CPM"}}
{"timestamp": 125.70000008642674, "ITS_PDU_Header": {"tmp": "tmp"}, "Basic_Container": {"tmp": "tmp"}, "HF_Container": {"sumo_id": "99", "location": [-383.4254150390625, -2.0], "speed": [-19.567870802166002, 0.0, 0], "yaw": -179.99996948242188}, "LF_Container": {"tmp": "tmp"}, "Special_Vehicle_Container": {"tmp": "tmp"}, "option": {"size": 190, "type": "CAM"}}
{"timestamp": 125.80000008791686, "ITS_PDU_Header": {"tmp": "tmp"}, "Management_Container": {"tmp": "tmp"}, "Station_Data_Container": {"sumo_id": "99", "location": [-385.38299560546875, -2.0], "speed": [-19.575805372360268, 0.0, 0], "yaw": -179.99996948242188}, "Sensor_Information_Container": [0, 1, 2, 3], "Perceived_Object_Container": [{"time": 125.80000008791686, "location": {"x": -253.5540975206963, "y": 5.718552737837178}, "speed": {"x": 14.972533956579358, "y": 0.0, "z": 0}, "pseudonym": 2}, {"time": 125.80000008791686, "location": {"x": -373.1792071385767, "y": -9.241342428796548}, "speed": {"x": -17.272338609809598, "y": 0.0, "z": 0}, "pseudonym": 0}], "option": {"size": 331, "type": "CPM"}}
