{"timestamp": 12.259999725967646, "ITS_PDU_Header": {"tmp": "tmp"}, "Basic_Container": {"tmp": "tmp"}, "HF_Container": {"sumo_id": "49", "location": [-72.2464599609375, -2.0], "speed": [-7224.6461575771755, -200.00000447034847, 0], "yaw": -179.99996948242188}, "LF_Container": {"tmp": "tmp"}, "Special_Vehicle_Container": {"tmp": "tmp"}, "option": {"size": 190, "type": "CAM"}}
{"timestamp": 12.259999725967646, "ITS_PDU_Header": {"tmp": "tmp"}, "Management_Container": {"tmp": "tmp"}, "Station_Data_Container": {"sumo_id": "49", "location": [-72.2464599609375, -2.0], "speed": [-7224.6461575771755, -200.00000447034847, 0], "yaw": -179.99996948242188}, "Sensor_Information_Container": [0, 1, 2, 3], "Perceived_Object_Container": [{"time": 12.259999725967646, "location": {"x": -42.59409158345007, "y": -2.145468358118161}, "speed": {"x": -3.7109375829459186, "y": 0.0, "z": 0}, "pseudonym": 0}], "option": {"size": 296, "type": "CPM"}}
{"timestamp": 12.369999723508954, "ITS_PDU_Header": {"tmp": "tmp"}, "Management_Container": {"tmp": "tmp"}, "Station_Data_Container": {"sumo_id": "49", "location": [-72.263427734375, -2.0], "speed": [-0.2807617250255136, 0.0, 0], "yaw": -179.99996948242188}, "Sensor_Information_Container": [0, 1, 2, 3], "Perceived_Object_Container": [{"time": 12.369999723508954, "location": {"x": -160.45762891114907, "y": -8.957558424723267}, "speed": {"x": -1.434326203934689, "y": 0.0, "z": 0}, "pseudonym": 1}, {"time": 12.369999723508954, "location": {"x": -162.43445206355625, "y": -8.631377233516716}, "speed": {"x": -1.434326203934689, "y": 0.0, "z": 0}, "pseudonym": 2}, {"time": 12.369999723508954, "location": {"x": -134.39923700314662, "y": 1.4042589790874187}, "speed": {"x": 19.648743114964883, "y": 0.0, "z": 0}, "pseudonym": 3}], "option": {"size": 366, "type": "CPM"}}
{"timestamp": 12.369999723508954, "ITS_PDU_Header": {"tmp": "tmp"}, "Basic_Container": {"tmp": "tmp"}, "HF_Container": {"sumo_id": "49", "location": [-72.263427734375, -2.0], "speed": [-0.2807617250255136, 0.0, 0], "yaw": -179.99996948242188}, "LF_Container": {"tmp": "tmp"}, "Special_Vehicle_Container": {"tmp": "tmp"}, "option": {"size": 190, "type": "CAM"}}
{"timestamp": 12.379999723285437, "ITS_PDU_Header": {"tmp": "tmp"}, "Management_Container": {"tmp": "tmp"}, "Station_Data_Container": {"sumo_id": "49", "location": [-72.26654052734375, -2.0], "speed": [-0.31127930383263464, 0.0, 0], "yaw": -179.99996948242188}, "Sensor_Information_Container": [0, 1, 2, 3], "Perceived_Object_Container": [{"time": 12.379999723285437, "location": {"x": 5.122600973638181, "y": 1.973666873629372}, "speed": {"x": 13.72070343168162, "y": 0.0, "z": 0}, "pseudonym": 4}], "option": {"size": 296, "type": "CPM"}}
{"timestamp": 12.46999972127378, "ITS_PDU_Header": {"tmp": "tmp"}, "Management_Container": {"tmp": "tmp"}, "Station_Data_Container": {"sumo_id": "49", "location": [-72.3055419921875, -2.0], "speed": [-0.5310058712439061, 0.0, 0], "yaw": -179.99996948242188}, "Sensor_Information_Container": [0, 1, 2, 3], "Perceived_Object_Container": [{"time": 12.46999972127378, "location": {"x": -107.90923537914057, "y": -4.918657728852404}, "speed": {"x": -14.409637773252378, "y": 0.0, "z": 0}, "pseudonym": 5}, {"time": 12.46999972127378, "location": {"x": -17.689236233470098, "y": -5.892279900793001}, "speed": {"x": -15.832519885134396, "y": 0.0, "z": 0}, "pseudonym": 6}], "option": {"size": 331, "type": "CPM"}}
{"timestamp": 12.569999719038606, "ITS_PDU_Header": {"tmp": "tmp"}, "Management_Container": {"tmp": "tmp"}, "Station_Data_Container": {"sumo_id": "49", "location": [-72.3720703125, -2.0], "speed": [-0.7759094411710524, 0.0, 0], "yaw": -179.99996948242188}, "Sensor_Information_Container": [0, 1, 2, 3], "Perceived_Object_Container": [{"time": 12.569999719038606, "location": {"x": -43.82677828538476, "y": -2.061960544583304}, "speed": {"x": -4.357910253656884, "y": 0.0, "z": 0}, "pseudonym": 0}], "option": {"size": 296, "type": "CPM"}}
{"timestamp": 12.669999716803432, "ITS_PDU_Header": {"tmp": "tmp"}, "Basic_Container": {"tmp": "tmp"}, "HF_Container": {"sumo_id": "49", "location": [-72.46307373046875, -2.0], "speed": [-1.0192871321578427, 0.0, 0], "yaw": -179.99996948242188}, "LF_Container": {"tmp": "tmp"}, "Special_Vehicle_Container": {"tmp": "tmp"}, "option": {"size": 190, "type": "CAM"}}
{"timestamp": 12.669999716803432, "ITS_PDU_Header": {"tmp": "tmp"}, "Management_Container": {"tmp": "tmp"}, "Station_Data_Container": {"sumo_id": "49", "location": [-72.46307373046875, -2.0], "speed": [-1.0192871321578427, 0.0, 0], "yaw": -179.99996948242188}, "Sensor_Information_Container": [0, 1, 2, 3], "Perceived_Object_Container": [{"time": 12.669999716803432, "location": {"x": 9.3107640432479, "y": 1.7851644488953589}, "speed": {"x": 14.270019850209799, "y": 0.0, "z": 0}, "pseudonym": 4}], "option": {"size": 296, "type": "CPM"}}
{"timestamp": 12.769999714568257, "ITS_PDU_Header": {"tmp": "tmp"}, "Management_Container": {"tmp": "tmp"}, "Station_Data_Container": {"sumo_id": "49", "location": [-72.57733154296875, -2.0], "speed": [-1.2451172153305385, 0.0, 0], "yaw": -179.99996948242188}, "Sensor_Information_Container": [0, 1, 2, 3], "Perceived_Object_Container": [{"time": 12.769999714568257, "location": {"x": -113.82726102464389, "y": -4.916530739895968}, "speed": {"x": -15.008545257342128, "y": 0.0, "z": 0}, "pseudonym": 5}, {"time": 12.769999714568257, "location": {"x": -22.554576962210085, "y": -5.368054857066389}, "speed": {"x": -16.387939819424, "y": 0.0, "z": 0}, "pseudonym": 6}], "option": {"size": 331, "type": "CPM"}}
{"timestamp": 12.869999712333083, "ITS_PDU_Header": {"tmp": "tmp"}, "Management_Container": {"tmp": "tmp"}, "Station_Data_Container": {"sumo_id": "49", "location": [-72.715087890625, -2.0], "speed": [-1.4892578457875068, 0.0, 0], "yaw": -179.99996948242188}, "Sensor_Information_Container": [0, 1, 2, 3], "Perceived_Object_Container": [{"time": 12.869999712333083, "location": {"x": -45.2303398193214, "y": -1.9456467759442373}, "speed": {"x": -4.949569812779944, "y": 0.0, "z": 0}, "pseudonym": 0}, {"time": 12.869999712333083, "location": {"x": -112.75546372576933, "y": -4.933680336308986}, "speed": {"x": -15.21606479323055, "y": 0.0, "z": 0}, "pseudonym": 7}], "option": {"size": 331, "type": "CPM"}}
{"timestamp": 12.969999710097909, "ITS_PDU_Header": {"tmp": "tmp"}, "Management_Container": {"tmp": "tmp"}, "Station_Data_Container": {"sumo_id": "49", "location": [-72.87493896484375, -2.0], "speed": [-1.697540321146108, 0.0, 0], "yaw": -179.99996948242188}, "Sensor_Information_Container": [0, 1, 2, 3], "Perceived_Object_Container": [{"time": 12.969999710097909, "location": {"x": 13.663402635254577, "y": 2.0892765389636225}, "speed": {"x": 14.868164394829371, "y": 0.0, "z": 0}, "pseudonym": 4}], "option": {"size": 296, "type": "CPM"}}
{"timestamp": 12.969999710097909, "ITS_PDU_Header": {"tmp": "tmp"}, "Basic_Container": {"tmp": "tmp"}, "HF_Container": {"sumo_id": "49", "location": [-72.87493896484375, -2.0], "speed": [-1.697540321146108, 0.0, 0], "yaw": -179.99996948242188}, "LF_Container": {"tmp": "tmp"}, "Special_Vehicle_Container": {"tmp": "tmp"}, "option": {"size": 190, "type": "CAM"}}
{"timestamp": 13.069999707862735, "ITS_PDU_Header": {"tmp": "tmp"}, "Management_Container": {"tmp": "tmp"}, "Station_Data_Container": {"sumo_id": "49", "location": [-73.055908203125, -2.0], "speed": [-1.9104004333257771, 0.0, 0], "yaw": -179.99996948242188}, "Sensor_Information_Container": [0, 1, 2, 3], "Perceived_Object_Container": [{"time": 13.069999707862735, "location": {"x": -116.67841940065017, "y": -4.921375174335377}, "speed": {"x": -15.613556257193302, "y": 0.0, "z": 0}, "pseudonym": 5}, {"time": 13.069999707862735, "location": {"x": 41.60825330724832, "y": 4.995444112626385}, "speed": {"x": 0.13427734675133257, "y": 0.0, "z": 0}, "pseudonym": 8}], "option": {"size": 331, "type": "CPM"}}
{"timestamp": 13.16999970562756, "ITS_PDU_Header": {"tmp": "tmp"}, "Management_Container": {"tmp": "tmp"}, "Station_Data_Container": {"sumo_id": "49", "location": [-73.25835418701172, -2.0], "speed": [-2.117157029744022, 0.0, 0], "yaw": -179.99996948242188}, "Sensor_Information_Container": [0, 1, 2, 3], "Perceived_Object_Container": [{"time": 13.16999970562756, "location": {"x": -46.8080964757145, "y": -2.0912682317434785}, "speed": {"x": -5.535888795611757, "y": 0.0, "z": 0}, "pseudonym": 0}, {"time": 13.16999970562756, "location": {"x": 22.08371059773539, "y": -8.412968369597792}, "speed": {"x": -16.894531627622207, "y": 0.0, "z": 0}, "pseudonym": 9}, {"time": 13.16999970562756, "location": {"x": -120.31235206541771, "y": -4.911537296650145}, "speed": {"x": -15.814972277320301, "y": 0.0, "z": 0}, "pseudonym": 10}], "option": {"size": 366, "type": "CPM"}}
{"timestamp": 13.269999703392386, "ITS_PDU_Header": {"tmp": "tmp"}, "Basic_Container": {"tmp": "tmp"}, "HF_Container": {"sumo_id": "49", "location": [-73.48247528076172, -2.0], "speed": [-2.343750052386896, 0.0, 0], "yaw": -179.99996948242188}, "LF_Container": {"tmp": "tmp"}, "Special_Vehicle_Container": {"tmp": "tmp"}, "option": {"size": 190, "type": "CAM"}}
{"timestamp": 13.269999703392386, "ITS_PDU_Header": {"tmp": "tmp"}, "Management_Container": {"tmp": "tmp"}, "Station_Data_Container": {"sumo_id": "49", "location": [-73.48247528076172, -2.0], "speed": [-2.343750052386896, 0.0, 0], "yaw": -179.99996948242188}, "Sensor_Information_Container": [0, 1, 2, 3], "Perceived_Object_Container": [{"time": 13.269999703392386, "location": {"x": 18.24881670903015, "y": 1.7347222439614864}, "speed": {"x": 15.484619486733216, "y": 0.0, "z": 0}, "pseudonym": 4}], "option": {"size": 296, "type": "CPM"}}
{"timestamp": 13.369999701157212, "ITS_PDU_Header": {"tmp": "tmp"}, "Management_Container": {"tmp": "tmp"}, "Station_Data_Container": {"sumo_id": "49", "location": [-73.72802734375, -2.0], "speed": [-2.5390625567524707, 0.0, 0], "yaw": -179.99996948242188}, "Sensor_Information_Container": [0, 1, 2, 3], "Perceived_Object_Container": [{"time": 13.369999701157212, "location": {"x": 40.973082322812076, "y": 4.994404279445953}, "speed": {"x": 0.878906269645086, "y": 0.0, "z": 0}, "pseudonym": 8}, {"time": 13.369999701157212, "location": {"x": -120.58407362369263, "y": -4.933694544784252}, "speed": {"x": -15.826416369372971, "y": 0.0, "z": 0}, "pseudonym": 7}], "option": {"size": 331, "type": "CPM"}}
{"timestamp": 13.469999698922038, "ITS_PDU_Header": {"tmp": "tmp"}, "Management_Container": {"tmp": "tmp"}, "Station_Data_Container": {"sumo_id": "49", "location": [-73.99261474609375, -2.0], "speed": [-2.728271545356621, 0.0, 0], "yaw": -179.99996948242188}, "Sensor_Information_Container": [0, 1, 2, 3], "Perceived_Object_Container": [{"time": 13.469999698922038, "location": {"x": -48.56026459117847, "y": -2.0153160848965457}, "speed": {"x": -6.164932388773539, "y": 0.0, "z": 0}, "pseudonym": 0}, {"time": 13.469999698922038, "location": {"x": -112.26494370467874, "y": 1.9300553739855606}, "speed": {"x": 20.111084433892767, "y": 0.0, "z": 0}, "pseudonym": 3}], "option": {"size": 331, "type": "CPM"}}
{"timestamp": 13.569999696686864, "ITS_PDU_Header": {"tmp": "tmp"}, "Management_Container": {"tmp": "tmp"}, "Station_Data_Container": {"sumo_id": "49", "location": [-74.274169921875, -2.0], "speed": [-2.8930664709150746, 0.0, 0], "yaw": -179.99996948242188}, "Sensor_Information_Container": [0, 1, 2, 3], "Perceived_Object_Container": [{"time": 13.569999696686864, "location": {"x": 22.977697250736178, "y": 1.7505779551817702}, "speed": {"x": 16.064453484068515, "y": 0.0, "z": 0}, "pseudonym": 4}], "option": {"size": 296, "type": "CPM"}}
{"timestamp": 13.569999696686864, "ITS_PDU_Header": {"tmp": "tmp"}, "Basic_Container": {"tmp": "tmp"}, "HF_Container": {"sumo_id": "49", "location": [-74.274169921875, -2.0], "speed": [-2.8930664709150746, 0.0, 0], "yaw": -179.99996948242188}, "LF_Container": {"tmp": "tmp"}, "Special_Vehicle_Container": {"tmp": "tmp"}, "option": {"size": 190, "type": "CAM"}}
{"timestamp": 13.769999692216516, "ITS_PDU_Header": {"tmp": "tmp"}, "Management_Container": {"tmp": "tmp"}, "Station_Data_Container": {"sumo_id": "49", "location": [-74.8934326171875, -2.0], "speed": [-3.278350903354978, 0.0, 0], "yaw": -179.99996948242188}, "Sensor_Information_Container": [0, 1, 2, 3], "Perceived_Object_Container": [{"time": 13.769999692216516, "location": {"x": -50.52004873530974, "y": -1.8613402716438474}, "speed": {"x": -6.756591947896599, "y": 0.0, "z": 0}, "pseudonym": 0}], "option": {"size": 296, "type": "CPM"}}
{"timestamp": 13.869999689981341, "ITS_PDU_Header": {"tmp": "tmp"}, "Management_Container": {"tmp": "tmp"}, "Station_Data_Container": {"sumo_id": "49", "location": [-75.23174285888672, -2.0], "speed": [-3.4667969524889504, 0.0, 0], "yaw": -179.99996948242188}, "Sensor_Information_Container": [0, 1, 2, 3], "Perceived_Object_Container": [{"time": 13.869999689981341, "location": {"x": -40.69353119723998, "y": -5.628132120251462}, "speed": {"x": -16.65039099716524, "y": 0.0, "z": 0}, "pseudonym": 6}, {"time": 13.869999689981341, "location": {"x": 27.90913648834352, "y": 1.9626297307096405}, "speed": {"x": 16.63818396564239, "y": 0.0, "z": 0}, "pseudonym": 4}, {"time": 13.869999689981341, "location": {"x": 40.58336438298217, "y": 4.9962888758062665}, "speed": {"x": 2.00195316974714, "y": 0.0, "z": 0}, "pseudonym": 8}], "option": {"size": 366, "type": "CPM"}}
{"timestamp": 13.869999689981341, "ITS_PDU_Header": {"tmp": "tmp"}, "Basic_Container": {"tmp": "tmp"}, "HF_Container": {"sumo_id": "49", "location": [-75.23174285888672, -2.0], "speed": [-3.4667969524889504, 0.0, 0], "yaw": -179.99996948242188}, "LF_Container": {"tmp": "tmp"}, "Special_Vehicle_Container": {"tmp": "tmp"}, "option": {"size": 190, "type": "CAM"}}
{"timestamp": 14.069999685510993, "ITS_PDU_Header": {"tmp": "tmp"}, "Management_Container": {"tmp": "tmp"}, "Station_Data_Container": {"sumo_id": "49", "location": [-75.97100067138672, -2.0], "speed": [-3.8818360242657963, 0.0, 0], "yaw": -179.99996948242188}, "Sensor_Information_Container": [0, 1, 2, 3], "Perceived_Object_Container": [{"time": 14.069999685510993, "location": {"x": -52.65510251954194, "y": -1.9706447076062075}, "speed": {"x": -7.3421479912582335, "y": 0.0, "z": 0}, "pseudonym": 0}, {"time": 14.069999685510993, "location": {"x": -166.01242241372438, "y": -9.815224046828927}, "speed": {"x": -4.8706055776165185, "y": 0.0, "z": 0}, "pseudonym": 1}], "option": {"size": 331, "type": "CPM"}}
{"timestamp": 14.169999683275819, "ITS_PDU_Header": {"tmp": "tmp"}, "Basic_Container": {"tmp": "tmp"}, "HF_Container": {"sumo_id": "49", "location": [-76.37041473388672, -2.0], "speed": [-4.082489104922617, 0.0, 0], "yaw": -179.99996948242188}, "LF_Container": {"tmp": "tmp"}, "Special_Vehicle_Container": {"tmp": "tmp"}, "option": {"size": 190, "type": "CAM"}}
{"timestamp": 14.169999683275819, "ITS_PDU_Header": {"tmp": "tmp"}, "Management_Container": {"tmp": "tmp"}, "Station_Data_Container": {"sumo_id": "49", "location": [-76.37041473388672, -2.0], "speed": [-4.082489104922617, 0.0, 0], "yaw": -179.99996948242188}, "Sensor_Information_Container": [0, 1, 2, 3], "Perceived_Object_Container": [{"time": 14.169999683275819, "location": {"x": 41.239332415104826, "y": 4.9994420973782026}, "speed": {"x": 2.6000977143667128, "y": 0.0, "z": 0}, "pseudonym": 8}], "option": {"size": 296, "type": "CPM"}}
{"timestamp": 14.269999681040645, "ITS_PDU_Header": {"tmp": "tmp"}, "Management_Container": {"tmp": "tmp"}, "Station_Data_Container": {"sumo_id": "49", "location": [-76.78948974609375, -2.0], "speed": [-4.290771580281218, 0.0, 0], "yaw": -179.99996948242188}, "Sensor_Information_Container": [0, 1, 2, 3], "Perceived_Object_Container": [{"time": 14.269999681040645, "location": {"x": 34.71211454589081, "y": 2.2265945931834215}, "speed": {"x": 17.431641014627537, "y": 0.0, "z": 0}, "pseudonym": 4}], "option": {"size": 296, "type": "CPM"}}
{"timestamp": 14.36999967880547, "ITS_PDU_Header": {"tmp": "tmp"}, "Management_Container": {"tmp": "tmp"}, "Station_Data_Container": {"sumo_id": "49", "location": [-77.22930145263672, -2.0], "speed": [-4.492187600408218, 0.0, 0], "yaw": -179.99996948242188}, "Sensor_Information_Container": [0, 1, 2, 3], "Perceived_Object_Container": [{"time": 14.36999967880547, "location": {"x": -54.939800287038516, "y": -1.7237041748468782}, "speed": {"x": -7.916259942567198, "y": 0.0, "z": 0}, "pseudonym": 0}, {"time": 14.36999967880547, "location": {"x": -167.47798991687793, "y": -9.23867308791102}, "speed": {"x": -5.450439574951818, "y": 0.0, "z": 0}, "pseudonym": 1}], "option": {"size": 331, "type": "CPM"}}
{"timestamp": 14.469999676570296, "ITS_PDU_Header": {"tmp": "tmp"}, "Basic_Container": {"tmp": "tmp"}, "HF_Container": {"sumo_id": "49", "location": [-77.68939208984375, -2.0], "speed": [-4.687500104773792, 0.0, 0], "yaw": -179.99996948242188}, "LF_Container": {"tmp": "tmp"}, "Special_Vehicle_Container": {"tmp": "tmp"}, "option": {"size": 190, "type": "CAM"}}
{"timestamp": 14.469999676570296, "ITS_PDU_Header": {"tmp": "tmp"}, "Management_Container": {"tmp": "tmp"}, "Station_Data_Container": {"sumo_id": "49", "location": [-77.68939208984375, -2.0], "speed": [-4.687500104773792, 0.0, 0], "yaw": -179.99996948242188}, "Sensor_Information_Container": [0, 1, 2, 3], "Perceived_Object_Container": [{"time": 14.469999676570296, "location": {"x": -139.2770496236962, "y": -4.9169723973986805}, "speed": {"x": -15.826416369372971, "y": 0.0, "z": 0}, "pseudonym": 5}, {"time": 14.469999676570296, "location": {"x": 1.4176973212734367, "y": -8.427155072965853}, "speed": {"x": -16.894531627622207, "y": 0.0, "z": 0}, "pseudonym": 9}], "option": {"size": 331, "type": "CPM"}}
{"timestamp": 14.569999674335122, "ITS_PDU_Header": {"tmp": "tmp"}, "Management_Container": {"tmp": "tmp"}, "Station_Data_Container": {"sumo_id": "49", "location": [-78.16802215576172, -2.0], "speed": [-4.86984263814634, 0.0, 0], "yaw": -179.99996948242188}, "Sensor_Information_Container": [0, 1, 2, 3], "Perceived_Object_Container": [{"time": 14.569999674335122, "location": {"x": -90.55046358223493, "y": 1.5859100757011684}, "speed": {"x": 20.123291465415615, "y": 0.0, "z": 0}, "pseudonym": 3}, {"time": 14.569999674335122, "location": {"x": -2.8065124377690154, "y": -8.410985897384759}, "speed": {"x": -16.888428111860783, "y": 0.0, "z": 0}, "pseudonym": 11}], "option": {"size": 331, "type": "CPM"}}
{"timestamp": 14.669999672099948, "ITS_PDU_Header": {"tmp": "tmp"}, "Management_Container": {"tmp": "tmp"}, "Station_Data_Container": {"sumo_id": "49", "location": [-78.6661376953125, -2.0], "speed": [-5.065918081982093, 0.0, 0], "yaw": -179.99996948242188}, "Sensor_Information_Container": [0, 1, 2, 3], "Perceived_Object_Container": [{"time": 14.669999672099948, "location": {"x": -57.40599114300923, "y": -2.0311986238935456}, "speed": {"x": -8.507919501690257, "y": 0.0, "z": 0}, "pseudonym": 0}, {"time": 14.669999672099948, "location": {"x": -169.2332761128033, "y": -9.294527327303722}, "speed": {"x": -6.04095472486961, "y": 0.0, "z": 0}, "pseudonym": 1}, {"time": 14.669999672099948, "location": {"x": 43.89618183351641, "y": 4.992748860438419}, "speed": {"x": 3.515625078580344, "y": 0.0, "z": 0}, "pseudonym": 8}], "option": {"size": 366, "type": "CPM"}}
{"timestamp": 14.769999669864774, "ITS_PDU_Header": {"tmp": "tmp"}, "Basic_Container": {"tmp": "tmp"}, "HF_Container": {"sumo_id": "49", "location": [-79.185302734375, -2.0], "speed": [-5.27954113363194, 0.0, 0], "yaw": -179.99996948242188}, "LF_Container": {"tmp": "tmp"}, "Special_Vehicle_Container": {"tmp": "tmp"}, "option": {"size": 190, "type": "CAM"}}
