{"timestamp": 119.99999999977648, "ITS_PDU_Header": {"tmp": "tmp"}, "Basic_Container": {"tmp": "tmp"}, "HF_Container": {"sumo_id": "99", "location": [-813.8935546875, -2.0], "speed": [-81389.3572879439, -200.00000447034847, 0], "yaw": -179.99996948242188}, "LF_Container": {"tmp": "tmp"}, "Special_Vehicle_Container": {"tmp": "tmp"}, "option": {"size": 190, "type": "CAM"}}
{"timestamp": 120.10999999731779, "ITS_PDU_Header": {"tmp": "tmp"}, "Basic_Container": {"tmp": "tmp"}, "HF_Container": {"sumo_id": "99", "location": [-814.2985229492188, -2.0], "speed": [-4.040527434062826, 0.0, 0], "yaw": -179.99996948242188}, "LF_Container": {"tmp": "tmp"}, "Special_Vehicle_Container": {"tmp": "tmp"}, "option": {"size": 190, "type": "CAM"}}
{"timestamp": 120.10999999731779, "ITS_PDU_Header": {"tmp": "tmp"}, "Management_Container": {"tmp": "tmp"}, "Station_Data_Container": {"sumo_id": "99", "location": [-814.2985229492188, -2.0], "speed": [-4.040527434062826, 0.0, 0], "yaw": -179.99996948242188}, "Sensor_Information_Container": [0, 1, 2, 3], "Perceived_Object_Container": [{"time": 120.10999999731779, "location": {"x": -840.0592813988773, "y": 5.1435516250012805}, "speed": {"x": 16.644287481403815, "y": 0.0, "z": 0}, "pseudonym": 0}, {"time": 120.10999999731779, "location": {"x": -875.4851692639277, "y": -6.134052563845398}, "speed": {"x": -16.162109736251303, "y": 0.0, "z": 0}, "pseudonym": 1}, {"time": 120.10999999731779, "location": {"x": -824.5583319239489, "y": -2.081298998282412}, "speed": {"x": -3.875732508504372, "y": 0.0, "z": 0}, "pseudonym": 2}, {"time": 120.10999999731779, "location": {"x": -825.5742838209367, "y": 1.7685539949260094}, "speed": {"x": 4.345703222134036, "y": 0.0, "z": 0}, "pseudonym": 3}, {"time": 120.10999999731779, "location": {"x": -781.6134481363046, "y": -8.990270894688779}, "speed": {"x": -11.669922135843086, "y": 0.0, "z": 0}, "pseudonym": 4}, {"time": 120.10999999731779, "location": {"x": -802.882728375438, "y": 1.7502375657627494}, "speed": {"x": 4.156494233529886, "y": 0.0, "z": 0}, "pseudonym": 5}, {"time": 120.10999999731779, "location": {"x": -767.50331962253, "y": 1.1698126005745488}, "speed": {"x": 3.8208008666515543, "y": 0.0, "z": 0}, "pseudonym": 6}, {"time": 120.10999999731779, "location": {"x": -802.7651265261775, "y": -1.922949576494472}, "speed": {"x": -4.241943454189824, "y": 0.0, "z": 0}, "pseudonym": 7}, {"time": 120.10999999731779, "location": {"x": -917.4701419789126, "y": -9.459164917149158}, "speed": {"x": -13.708496400158772, "y": 0.0, "z": 0}, "pseudonym": 8}, {"time": 120.10999999731779, "location": {"x": -837.0181393255166, "y": 1.8601699345259661}, "speed": {"x": 4.406738379748278, "y": 0.0, "z": 0}, "pseudonym": 9}, {"time": 120.10999999731779, "location": {"x": -836.1935548134325, "y": -5.347328585779283}, "speed": {"x": -16.66870154444951, "y": 0.0, "z": 0}, "pseudonym": 10}, {"time": 120.10999999731779, "location": {"x": -873.02496465941, "y": -8.641766003343351}, "speed": {"x": -14.147949534981315, "y": 0.0, "z": 0}, "pseudonym": 11}, {"time": 120.10999999731779, "location": {"x": -850.3504285980887, "y": 1.1717826488686907}, "speed": {"x": 4.431152442793975, "y": 0.0, "z": 0}, "pseudonym": 12}, {"time": 120.10999999731779, "location": {"x": -763.8435975118724, "y": -6.282169002549124}, "speed": {"x": -16.68090857597236, "y": 0.0, "z": 0}, "pseudonym": 13}, {"time": 120.10999999731779, "location": {"x": -786.5944701511268, "y": -5.141326099523382}, "speed": {"x": -16.632080449880966, "y": 0.0, "z": 0}, "pseudonym": 14}, {"time": 120.10999999731779, "location": {"x": -790.7693648187806, "y": 1.632790184235082}, "speed": {"x": 4.040527434062826, "y": 0.0, "z": 0}, "pseudonym": 15}, {"time": 120.10999999731779, "location": {"x": -788.3493186813186, "y": -5.964446436100456}, "speed": {"x": -16.632080449880966, "y": 0.0, "z": 0}, "pseudonym": 16}, {"time": 120.10999999731779, "location": {"x": -756.1632202307042, "y": 1.45270201415036}, "speed": {"x": 3.7109375829459186, "y": 0.0, "z": 0}, "pseudonym": 17}, {"time": 120.10999999731779, "location": {"x": -780.666103992426, "y": 5.900493253663619}, "speed": {"x": 16.68090857597236, "y": 0.0, "z": 0}, "pseudonym": 18}, {"time": 120.10999999731779, "location": {"x": -814.1215933210021, "y": 1.4742466507546892}, "speed": {"x": 4.2724610329969455, "y": 0.0, "z": 0}, "pseudonym": 19}], "option": {"size": 961, "type": "CPM"}}
{"timestamp": 120.2199999948591, "ITS_PDU_Header": {"tmp": "tmp"}, "Management_Container": {"tmp": "tmp"}, "Station_Data_Container": {"sumo_id": "99", "location": [-814.7427978515625, -2.0], "speed": [-4.040527434062826, 0.0, 0], "yaw": -179.99996948242188}, "Sensor_Information_Container": [0, 1, 2, 3], "Perceived_Object_Container": [{"time": 120.20999999508261, "location": {"x": -787.9520235546785, "y": -5.152352340218993}, "speed": {"x": -16.644287481403815, "y": 0.0, "z": 0}, "pseudonym": 20}], "option": {"size": 296, "type": "CPM"}}
{"timestamp": 120.31999999262392, "ITS_PDU_Header": {"tmp": "tmp"}, "Management_Container": {"tmp": "tmp"}, "Station_Data_Container": {"sumo_id": "99", "location": [-815.1452026367188, -2.0], "speed": [-4.016113371017129, 0.0, 0], "yaw": -179.99996948242188}, "Sensor_Information_Container": [0, 1, 2, 3], "Perceived_Object_Container": [{"time": 120.30999999284744, "location": {"x": -782.3331429611733, "y": -8.523588700091125}, "speed": {"x": -12.109375270665629, "y": 0.0, "z": 0}, "pseudonym": 21}, {"time": 120.30999999284744, "location": {"x": -694.6953349025175, "y": -9.394078379740435}, "speed": {"x": -10.076904522111368, "y": 0.0, "z": 0}, "pseudonym": 22}], "option": {"size": 331, "type": "CPM"}}
{"timestamp": 120.40999999061226, "ITS_PDU_Header": {"tmp": "tmp"}, "Management_Container": {"tmp": "tmp"}, "Station_Data_Container": {"sumo_id": "99", "location": [-815.5061645507812, -2.0], "speed": [-4.00390633949428, 0.0, 0], "yaw": -179.99996948242188}, "Sensor_Information_Container": [0, 1, 2, 3], "Perceived_Object_Container": [{"time": 120.40999999061226, "location": {"x": -785.0752871116833, "y": -8.805342208715434}, "speed": {"x": -12.274170196224082, "y": 0.0, "z": 0}, "pseudonym": 4}, {"time": 120.40999999061226, "location": {"x": -744.4517670803541, "y": -9.710064483323643}, "speed": {"x": -12.768554972899445, "y": 0.0, "z": 0}, "pseudonym": 23}], "option": {"size": 331, "type": "CPM"}}
