{"timestamp": 16.119999639689922, "ITS_PDU_Header": {"tmp": "tmp"}, "Management_Container": {"tmp": "tmp"}, "Station_Data_Container": {"sumo_id": "64", "location": [-354.200927734375, 5.75], "speed": [0.2807617250255136, 0.0, 0], "yaw": 0.0}, "Sensor_Information_Container": [0, 1, 2, 3], "Perceived_Object_Container": [{"time": 16.119999639689922, "location": {"x": -318.6180129015333, "y": -1.7667291676064594}, "speed": {"x": -19.958496539857162, "y": 0.0, "z": 0}, "pseudonym": 0}, {"time": 16.119999639689922, "location": {"x": -258.99465041982137, "y": 9.053466987940988}, "speed": {"x": 16.656494512926663, "y": 0.0, "z": 0}, "pseudonym": 1}, {"time": 16.119999639689922, "location": {"x": -317.1873497709718, "y": 1.8787583082546522}, "speed": {"x": 18.893433039488638, "y": 0.0, "z": 0}, "pseudonym": 2}, {"time": 16.119999639689922, "location": {"x": -257.13993662030987, "y": 8.411616621845518}, "speed": {"x": 16.656494512926663, "y": 0.0, "z": 0}, "pseudonym": 3}, {"time": 16.119999639689922, "location": {"x": -435.12881296371694, "y": -2.03938032110409}, "speed": {"x": -9.301758020410494, "y": 0.0, "z": 0}, "pseudonym": 4}, {"time": 16.119999639689922, "location": {"x": -466.5789043456705, "y": 2.0197473948559086}, "speed": {"x": 4.882812609139367, "y": 0.0, "z": 0}, "pseudonym": 5}, {"time": 16.119999639689922, "location": {"x": -372.29538630782577, "y": -8.532279066410608}, "speed": {"x": -17.56591836137887, "y": 0.0, "z": 0}, "pseudonym": 6}, {"time": 16.119999639689922, "location": {"x": -474.92272764834274, "y": -1.2040224001281352}, "speed": {"x": -3.491211015534647, "y": 0.0, "z": 0}, "pseudonym": 7}, {"time": 16.119999639689922, "location": {"x": -422.3667087922755, "y": -8.41420171992151}, "speed": {"x": -18.847656671277957, "y": 0.0, "z": 0}, "pseudonym": 8}, {"time": 16.119999639689922, "location": {"x": -468.32546156492356, "y": 2.6068633781488044}, "speed": {"x": 4.882812609139367, "y": 0.0, "z": 0}, "pseudonym": 9}], "option": {"size": 611, "type": "CPM"}}
{"timestamp": 16.119999639689922, "ITS_PDU_Header": {"tmp": "tmp"}, "Basic_Container": {"tmp": "tmp"}, "HF_Container": {"sumo_id": "64", "location": [-354.200927734375, 5.75], "speed": [0.2807617250255136, 0.0, 0], "yaw": 0.0}, "LF_Container": {"tmp": "tmp"}, "Special_Vehicle_Container": {"tmp": "tmp"}, "option": {"size": 190, "type": "CAM"}}
{"timestamp": 16.319999635219574, "ITS_PDU_Header": {"tmp": "tmp"}, "Basic_Container": {"tmp": "tmp"}, "HF_Container": {"sumo_id": "64", "location": [-354.09197998046875, 5.75], "speed": [0.7812500174622987, 0.0, 0], "yaw": 0.0}, "LF_Container": {"tmp": "tmp"}, "Special_Vehicle_Container": {"tmp": "tmp"}, "option": {"size": 190, "type": "CAM"}}
{"timestamp": 16.4199996329844, "ITS_PDU_Header": {"tmp": "tmp"}, "Management_Container": {"tmp": "tmp"}, "Station_Data_Container": {"sumo_id": "64", "location": [-354.0004577636719, 5.75], "speed": [1.0192871321578427, 0.0, 0], "yaw": 0.0}, "Sensor_Information_Container": [0, 1, 2, 3], "Perceived_Object_Container": [{"time": 16.4199996329844, "location": {"x": -377.3323651428527, "y": -8.52437642943218}, "speed": {"x": -18.194580484805567, "y": 0.0, "z": 0}, "pseudonym": 6}, {"time": 16.4199996329844, "location": {"x": -465.02345274865047, "y": 2.1384924122221096}, "speed": {"x": 5.43823254342897, "y": 0.0, "z": 0}, "pseudonym": 5}, {"time": 16.4199996329844, "location": {"x": -475.492949239311, "y": -1.2792158351508558}, "speed": {"x": -4.101562591677068, "y": 0.0, "z": 0}, "pseudonym": 7}], "option": {"size": 366, "type": "CPM"}}
{"timestamp": 16.61999962851405, "ITS_PDU_Header": {"tmp": "tmp"}, "Management_Container": {"tmp": "tmp"}, "Station_Data_Container": {"sumo_id": "64", "location": [-353.7474060058594, 5.75], "speed": [1.4770508142646583, 0.0, 0], "yaw": 0.0}, "Sensor_Information_Container": [0, 1, 2, 3], "Perceived_Object_Container": [{"time": 16.61999962851405, "location": {"x": -233.5823255349893, "y": -6.2294592361587275}, "speed": {"x": -0.8651733591818815, "y": 0.0, "z": 0}, "pseudonym": 10}, {"time": 16.61999962851405, "location": {"x": -439.624522197787, "y": -1.975221607943022}, "speed": {"x": -8.734131054598041, "y": 0.0, "z": 0}, "pseudonym": 4}], "option": {"size": 331, "type": "CPM"}}
{"timestamp": 16.61999962851405, "ITS_PDU_Header": {"tmp": "tmp"}, "Basic_Container": {"tmp": "tmp"}, "HF_Container": {"sumo_id": "64", "location": [-353.7474060058594, 5.75], "speed": [1.4770508142646583, 0.0, 0], "yaw": 0.0}, "LF_Container": {"tmp": "tmp"}, "Special_Vehicle_Container": {"tmp": "tmp"}, "option": {"size": 190, "type": "CAM"}}
{"timestamp": 16.719999626278877, "ITS_PDU_Header": {"tmp": "tmp"}, "Management_Container": {"tmp": "tmp"}, "Station_Data_Container": {"sumo_id": "64", "location": [-353.5867919921875, 5.75], "speed": [1.7028808974373542, 0.0, 0], "yaw": 0.0}, "Sensor_Information_Container": [0, 1, 2, 3], "Perceived_Object_Container": [{"time": 16.719999626278877, "location": {"x": -463.2939613677005, "y": 2.371127518671666}, "speed": {"x": 6.039428845929254, "y": 0.0, "z": 0}, "pseudonym": 5}, {"time": 16.719999626278877, "location": {"x": -384.19702917107355, "y": -8.484005257229928}, "speed": {"x": -18.820190850351548, "y": 0.0, "z": 0}, "pseudonym": 6}, {"time": 16.719999626278877, "location": {"x": -434.6085342471004, "y": -8.416923066039466}, "speed": {"x": -18.847656671277957, "y": 0.0, "z": 0}, "pseudonym": 11}], "option": {"size": 366, "type": "CPM"}}
